<?xml version='1.0' encoding='UTF-8'?>
<ATTACHMENTSLOTLIST>
	<ATTACHMENTSLOT>
		<uiSlotIndex>0</uiSlotIndex>
		<szSlotName>别碰我</szSlotName>
		<nasAttachmentClass>0</nasAttachmentClass>
		<nasLayoutClass>1</nasLayoutClass>
		<usDescPanelPosX>0</usDescPanelPosX>
		<usDescPanelPosY>0</usDescPanelPosY>
		<fMultiShot>0</fMultiShot>
		<fBigSlot>0</fBigSlot>
		<ubPocketMapping>0</ubPocketMapping>
	</ATTACHMENTSLOT>
	<ATTACHMENTSLOT>
		<uiSlotIndex>1</uiSlotIndex>
		<szSlotName>默认插槽 1</szSlotName>
		<nasAttachmentClass>1</nasAttachmentClass>
		<nasLayoutClass>1</nasLayoutClass>
		<usDescPanelPosX>187</usDescPanelPosX>
		<usDescPanelPosY>66</usDescPanelPosY>
		<fMultiShot>0</fMultiShot>
		<fBigSlot>0</fBigSlot>
		<ubPocketMapping>0</ubPocketMapping>
	</ATTACHMENTSLOT>
	<ATTACHMENTSLOT>
		<uiSlotIndex>2</uiSlotIndex>
		<szSlotName>默认插槽 2</szSlotName>
		<nasAttachmentClass>1</nasAttachmentClass>
		<nasLayoutClass>1</nasLayoutClass>
		<usDescPanelPosX>187</usDescPanelPosX>
		<usDescPanelPosY>95</usDescPanelPosY>
		<fMultiShot>0</fMultiShot>
		<fBigSlot>0</fBigSlot>
		<ubPocketMapping>0</ubPocketMapping>
	</ATTACHMENTSLOT>
	<ATTACHMENTSLOT>
		<uiSlotIndex>3</uiSlotIndex>
		<szSlotName>默认插槽 3</szSlotName>
		<nasAttachmentClass>1</nasAttachmentClass>
		<nasLayoutClass>1</nasLayoutClass>
		<usDescPanelPosX>224</usDescPanelPosX>
		<usDescPanelPosY>66</usDescPanelPosY>
		<fMultiShot>0</fMultiShot>
		<fBigSlot>0</fBigSlot>
		<ubPocketMapping>0</ubPocketMapping>
	</ATTACHMENTSLOT>
	<ATTACHMENTSLOT>
		<uiSlotIndex>4</uiSlotIndex>
		<szSlotName>默认插槽 4</szSlotName>
		<nasAttachmentClass>1</nasAttachmentClass>
		<nasLayoutClass>1</nasLayoutClass>
		<usDescPanelPosX>224</usDescPanelPosX>
		<usDescPanelPosY>94</usDescPanelPosY>
		<fMultiShot>0</fMultiShot>
		<fBigSlot>0</fBigSlot>
		<ubPocketMapping>0</ubPocketMapping>
	</ATTACHMENTSLOT>
	<ATTACHMENTSLOT>
		<uiSlotIndex>5</uiSlotIndex>
		<szSlotName>枪口附件</szSlotName>
		<nasAttachmentClass>2</nasAttachmentClass>
		<nasLayoutClass>1</nasLayoutClass>
		<usDescPanelPosX>10</usDescPanelPosX>
		<usDescPanelPosY>66</usDescPanelPosY>
		<fMultiShot>0</fMultiShot>
		<fBigSlot>0</fBigSlot>
		<ubPocketMapping>0</ubPocketMapping>
	</ATTACHMENTSLOT>
	<ATTACHMENTSLOT>
		<uiSlotIndex>6</uiSlotIndex>
		<szSlotName>激光附件</szSlotName>
		<nasAttachmentClass>4</nasAttachmentClass>
		<nasLayoutClass>1</nasLayoutClass>
		<usDescPanelPosX>67</usDescPanelPosX>
		<usDescPanelPosY>122</usDescPanelPosY>
		<fMultiShot>0</fMultiShot>
		<fBigSlot>0</fBigSlot>
		<ubPocketMapping>0</ubPocketMapping>
	</ATTACHMENTSLOT>
	<ATTACHMENTSLOT>
		<uiSlotIndex>7</uiSlotIndex>
		<szSlotName>共轴瞄准镜</szSlotName>
		<nasAttachmentClass>8</nasAttachmentClass>
		<nasLayoutClass>1</nasLayoutClass>
		<usDescPanelPosX>67</usDescPanelPosX>
		<usDescPanelPosY>38</usDescPanelPosY>
		<fMultiShot>0</fMultiShot>
		<fBigSlot>0</fBigSlot>
		<ubPocketMapping>0</ubPocketMapping>
	</ATTACHMENTSLOT>
	<ATTACHMENTSLOT>
		<uiSlotIndex>8</uiSlotIndex>
		<szSlotName>战斗光学/瞄准镜 - 如果你能看到这个，请对武器使用物品转换！</szSlotName>
		<nasAttachmentClass>16</nasAttachmentClass>
		<nasLayoutClass>1</nasLayoutClass>
		<usDescPanelPosX>107</usDescPanelPosX>
		<usDescPanelPosY>38</usDescPanelPosY>
		<fMultiShot>0</fMultiShot>
		<fBigSlot>0</fBigSlot>
		<ubPocketMapping>0</ubPocketMapping>
	</ATTACHMENTSLOT>
	<ATTACHMENTSLOT>
		<uiSlotIndex>9</uiSlotIndex>
		<szSlotName>枪托附件</szSlotName>
		<nasAttachmentClass>32</nasAttachmentClass>
		<nasLayoutClass>1</nasLayoutClass>
		<usDescPanelPosX>225</usDescPanelPosX>
		<usDescPanelPosY>80</usDescPanelPosY>
		<fMultiShot>0</fMultiShot>
		<fBigSlot>0</fBigSlot>
		<ubPocketMapping>0</ubPocketMapping>
	</ATTACHMENTSLOT>
	<ATTACHMENTSLOT>
		<uiSlotIndex>10</uiSlotIndex>
		<szSlotName>弹匣适配器</szSlotName>
		<nasAttachmentClass>64</nasAttachmentClass>
		<nasLayoutClass>1</nasLayoutClass>
		<usDescPanelPosX>107</usDescPanelPosX>
		<usDescPanelPosY>150</usDescPanelPosY>
		<fMultiShot>0</fMultiShot>
		<fBigSlot>0</fBigSlot>
		<ubPocketMapping>0</ubPocketMapping>
	</ATTACHMENTSLOT>
	<ATTACHMENTSLOT>
		<uiSlotIndex>11</uiSlotIndex>
		<szSlotName>内部附件</szSlotName>
		<nasAttachmentClass>128</nasAttachmentClass>
		<nasLayoutClass>1</nasLayoutClass>
		<usDescPanelPosX>107</usDescPanelPosX>
		<usDescPanelPosY>122</usDescPanelPosY>
		<fMultiShot>0</fMultiShot>
		<fBigSlot>0</fBigSlot>
		<ubPocketMapping>0</ubPocketMapping>
	</ATTACHMENTSLOT>
	<ATTACHMENTSLOT>
		<uiSlotIndex>12</uiSlotIndex>
		<szSlotName>外部：扳机组</szSlotName>
		<nasAttachmentClass>256</nasAttachmentClass>
		<nasLayoutClass>1</nasLayoutClass>
		<usDescPanelPosX>147</usDescPanelPosX>
		<usDescPanelPosY>122</usDescPanelPosY>
		<fMultiShot>0</fMultiShot>
		<fBigSlot>0</fBigSlot>
		<ubPocketMapping>0</ubPocketMapping>
	</ATTACHMENTSLOT>
	<ATTACHMENTSLOT>
		<uiSlotIndex>13</uiSlotIndex>
		<szSlotName>下挂附件</szSlotName>
		<nasAttachmentClass>512</nasAttachmentClass>
		<nasLayoutClass>1</nasLayoutClass>
		<usDescPanelPosX>67</usDescPanelPosX>
		<usDescPanelPosY>150</usDescPanelPosY>
		<fMultiShot>0</fMultiShot>
		<fBigSlot>0</fBigSlot>
		<ubPocketMapping>0</ubPocketMapping>
	</ATTACHMENTSLOT>
	<ATTACHMENTSLOT>
		<uiSlotIndex>14</uiSlotIndex>
		<szSlotName>步枪榴弹，单发</szSlotName>
		<nasAttachmentClass>1024</nasAttachmentClass>
		<nasLayoutClass>1</nasLayoutClass>
		<usDescPanelPosX>27</usDescPanelPosX>
		<usDescPanelPosY>150</usDescPanelPosY>
		<fMultiShot>0</fMultiShot>
		<fBigSlot>0</fBigSlot>
		<ubPocketMapping>0</ubPocketMapping>
	</ATTACHMENTSLOT>
	<ATTACHMENTSLOT>
		<uiSlotIndex>15</uiSlotIndex>
		<szSlotName>火箭发射器，单发</szSlotName>
		<nasAttachmentClass>2048</nasAttachmentClass>
		<nasLayoutClass>1</nasLayoutClass>
		<usDescPanelPosX>10</usDescPanelPosX>
		<usDescPanelPosY>150</usDescPanelPosY>
		<fMultiShot>0</fMultiShot>
		<fBigSlot>1</fBigSlot>
		<ubPocketMapping>0</ubPocketMapping>
	</ATTACHMENTSLOT>
	<ATTACHMENTSLOT>
		<uiSlotIndex>16</uiSlotIndex>
		<szSlotName>步枪榴弹 1</szSlotName>
		<nasAttachmentClass>1024</nasAttachmentClass>
		<nasLayoutClass>2</nasLayoutClass>
		<usDescPanelPosX>225</usDescPanelPosX>
		<usDescPanelPosY>150</usDescPanelPosY>
		<fMultiShot>1</fMultiShot>
		<fBigSlot>0</fBigSlot>
		<ubPocketMapping>0</ubPocketMapping>
	</ATTACHMENTSLOT>
	<ATTACHMENTSLOT>
		<uiSlotIndex>17</uiSlotIndex>
		<szSlotName>步枪榴弹 2</szSlotName>
		<nasAttachmentClass>1024</nasAttachmentClass>
		<nasLayoutClass>2</nasLayoutClass>
		<usDescPanelPosX>225</usDescPanelPosX>
		<usDescPanelPosY>122</usDescPanelPosY>
		<fMultiShot>1</fMultiShot>
		<fBigSlot>0</fBigSlot>
		<ubPocketMapping>0</ubPocketMapping>
	</ATTACHMENTSLOT>
	<ATTACHMENTSLOT>
		<uiSlotIndex>18</uiSlotIndex>
		<szSlotName>步枪榴弹 3</szSlotName>
		<nasAttachmentClass>1024</nasAttachmentClass>
		<nasLayoutClass>2</nasLayoutClass>
		<usDescPanelPosX>225</usDescPanelPosX>
		<usDescPanelPosY>94</usDescPanelPosY>
		<fMultiShot>1</fMultiShot>
		<fBigSlot>0</fBigSlot>
		<ubPocketMapping>0</ubPocketMapping>
	</ATTACHMENTSLOT>
	<ATTACHMENTSLOT>
		<uiSlotIndex>19</uiSlotIndex>
		<szSlotName>步枪榴弹 4</szSlotName>
		<nasAttachmentClass>1024</nasAttachmentClass>
		<nasLayoutClass>2</nasLayoutClass>
		<usDescPanelPosX>225</usDescPanelPosX>
		<usDescPanelPosY>66</usDescPanelPosY>
		<fMultiShot>1</fMultiShot>
		<fBigSlot>0</fBigSlot>
		<ubPocketMapping>0</ubPocketMapping>
	</ATTACHMENTSLOT>
	<ATTACHMENTSLOT>
		<uiSlotIndex>20</uiSlotIndex>
		<szSlotName>步枪榴弹 5</szSlotName>
		<nasAttachmentClass>1024</nasAttachmentClass>
		<nasLayoutClass>2</nasLayoutClass>
		<usDescPanelPosX>225</usDescPanelPosX>
		<usDescPanelPosY>38</usDescPanelPosY>
		<fMultiShot>1</fMultiShot>
		<fBigSlot>0</fBigSlot>
		<ubPocketMapping>0</ubPocketMapping>
	</ATTACHMENTSLOT>
	<ATTACHMENTSLOT>
		<uiSlotIndex>21</uiSlotIndex>
		<szSlotName>步枪榴弹 6</szSlotName>
		<nasAttachmentClass>1024</nasAttachmentClass>
		<nasLayoutClass>2</nasLayoutClass>
		<usDescPanelPosX>225</usDescPanelPosX>
		<usDescPanelPosY>10</usDescPanelPosY>
		<fMultiShot>1</fMultiShot>
		<fBigSlot>0</fBigSlot>
		<ubPocketMapping>0</ubPocketMapping>
	</ATTACHMENTSLOT>
	<ATTACHMENTSLOT>
		<uiSlotIndex>22</uiSlotIndex>
		<szSlotName>火箭发射器插槽 1</szSlotName>
		<nasAttachmentClass>2048</nasAttachmentClass>
		<nasLayoutClass>2</nasLayoutClass>
		<usDescPanelPosX>10</usDescPanelPosX>
		<usDescPanelPosY>12</usDescPanelPosY>
		<fMultiShot>1</fMultiShot>
		<fBigSlot>1</fBigSlot>
		<ubPocketMapping>0</ubPocketMapping>
	</ATTACHMENTSLOT>
	<ATTACHMENTSLOT>
		<uiSlotIndex>23</uiSlotIndex>
		<szSlotName>火箭发射器插槽 2</szSlotName>
		<nasAttachmentClass>2048</nasAttachmentClass>
		<nasLayoutClass>2</nasLayoutClass>
		<usDescPanelPosX>10</usDescPanelPosX>
		<usDescPanelPosY>150</usDescPanelPosY>
		<fMultiShot>1</fMultiShot>
		<fBigSlot>1</fBigSlot>
		<ubPocketMapping>0</ubPocketMapping>
	</ATTACHMENTSLOT>
	<ATTACHMENTSLOT>
		<uiSlotIndex>24</uiSlotIndex>
		<szSlotName>火箭发射器插槽 3</szSlotName>
		<nasAttachmentClass>2048</nasAttachmentClass>
		<nasLayoutClass>2</nasLayoutClass>
		<usDescPanelPosX>187</usDescPanelPosX>
		<usDescPanelPosY>12</usDescPanelPosY>
		<fMultiShot>1</fMultiShot>
		<fBigSlot>1</fBigSlot>
		<ubPocketMapping>0</ubPocketMapping>
	</ATTACHMENTSLOT>
	<ATTACHMENTSLOT>
		<uiSlotIndex>25</uiSlotIndex>
		<szSlotName>火箭发射器插槽 4</szSlotName>
		<nasAttachmentClass>2048</nasAttachmentClass>
		<nasLayoutClass>2</nasLayoutClass>
		<usDescPanelPosX>187</usDescPanelPosX>
		<usDescPanelPosY>150</usDescPanelPosY>
		<fMultiShot>1</fMultiShot>
		<fBigSlot>1</fBigSlot>
		<ubPocketMapping>0</ubPocketMapping>
	</ATTACHMENTSLOT>
	<ATTACHMENTSLOT>
		<uiSlotIndex>26</uiSlotIndex>
		<szSlotName>使用此物品的物品转换来重新创建附件。</szSlotName>
		<nasAttachmentClass>4096</nasAttachmentClass>
		<nasLayoutClass>1</nasLayoutClass>
		<usDescPanelPosX>147</usDescPanelPosX>
		<usDescPanelPosY>38</usDescPanelPosY>
		<fMultiShot>0</fMultiShot>
		<fBigSlot>0</fBigSlot>
		<ubPocketMapping>0</ubPocketMapping>
	</ATTACHMENTSLOT>
	<ATTACHMENTSLOT>
		<uiSlotIndex>27</uiSlotIndex>
		<szSlotName>使用此物品的物品转换来重新创建附件。</szSlotName>
		<nasAttachmentClass>8192</nasAttachmentClass>
		<nasLayoutClass>1</nasLayoutClass>
		<usDescPanelPosX>147</usDescPanelPosX>
		<usDescPanelPosY>10</usDescPanelPosY>
		<fMultiShot>0</fMultiShot>
		<fBigSlot>0</fBigSlot>
		<ubPocketMapping>0</ubPocketMapping>
	</ATTACHMENTSLOT>
	<ATTACHMENTSLOT>
		<uiSlotIndex>28</uiSlotIndex>
		<szSlotName>嵌套附件（瞄准镜）</szSlotName>
		<nasAttachmentClass>16384</nasAttachmentClass>
		<nasLayoutClass>1</nasLayoutClass>
		<usDescPanelPosX>107</usDescPanelPosX>
		<usDescPanelPosY>10</usDescPanelPosY>
		<fMultiShot>0</fMultiShot>
		<fBigSlot>0</fBigSlot>
		<ubPocketMapping>0</ubPocketMapping>
	</ATTACHMENTSLOT>	
	<ATTACHMENTSLOT>
		<uiSlotIndex>29</uiSlotIndex>
		<szSlotName>使用此物品的物品转换来重新创建附件。</szSlotName>
		<nasAttachmentClass>32768</nasAttachmentClass>
		<nasLayoutClass>1</nasLayoutClass>
		<usDescPanelPosX>225</usDescPanelPosX>
		<usDescPanelPosY>10</usDescPanelPosY>
		<fMultiShot>0</fMultiShot>
		<fBigSlot>0</fBigSlot>
		<ubPocketMapping>0</ubPocketMapping>
	</ATTACHMENTSLOT>
	<ATTACHMENTSLOT>
		<uiSlotIndex>30</uiSlotIndex>
		<szSlotName>使用此物品的物品转换来重新创建附件。</szSlotName>
		<nasAttachmentClass>65536</nasAttachmentClass>
		<nasLayoutClass>1</nasLayoutClass>
		<usDescPanelPosX>225</usDescPanelPosX>
		<usDescPanelPosY>38</usDescPanelPosY>
		<fMultiShot>0</fMultiShot>
		<fBigSlot>0</fBigSlot>
		<ubPocketMapping>0</ubPocketMapping>
	</ATTACHMENTSLOT>
	<ATTACHMENTSLOT>
		<uiSlotIndex>31</uiSlotIndex>
		<szSlotName>使用此物品的物品转换来重新创建附件。</szSlotName>
		<nasAttachmentClass>131072</nasAttachmentClass>
		<nasLayoutClass>1</nasLayoutClass>
		<usDescPanelPosX>225</usDescPanelPosX>
		<usDescPanelPosY>66</usDescPanelPosY>
		<fMultiShot>0</fMultiShot>
		<fBigSlot>0</fBigSlot>
		<ubPocketMapping>0</ubPocketMapping>
	</ATTACHMENTSLOT>
	<ATTACHMENTSLOT>
		<uiSlotIndex>32</uiSlotIndex>
		<szSlotName>刀插槽</szSlotName>
		<nasAttachmentClass>262144</nasAttachmentClass>
		<nasLayoutClass>1</nasLayoutClass>
		<usDescPanelPosX>10</usDescPanelPosX>
		<usDescPanelPosY>94</usDescPanelPosY>
		<fMultiShot>0</fMultiShot>
		<fBigSlot>0</fBigSlot>
		<ubPocketMapping>0</ubPocketMapping>
	</ATTACHMENTSLOT>	
	<ATTACHMENTSLOT>
		<uiSlotIndex>33</uiSlotIndex>
		<szSlotName>步枪背带</szSlotName>
		<nasAttachmentClass>524288</nasAttachmentClass>
		<nasLayoutClass>1</nasLayoutClass>
		<usDescPanelPosX>187</usDescPanelPosX>
		<usDescPanelPosY>94</usDescPanelPosY>
		<fMultiShot>0</fMultiShot>
		<fBigSlot>0</fBigSlot>
		<ubPocketMapping>0</ubPocketMapping>
	</ATTACHMENTSLOT>
	<ATTACHMENTSLOT>
		<uiSlotIndex>34</uiSlotIndex>
		<szSlotName>清洁工具包</szSlotName>
		<nasAttachmentClass>1048576</nasAttachmentClass>
		<nasLayoutClass>1</nasLayoutClass>
		<usDescPanelPosX>187</usDescPanelPosX>
		<usDescPanelPosY>66</usDescPanelPosY>
		<fMultiShot>0</fMultiShot>
		<fBigSlot>0</fBigSlot>
		<ubPocketMapping>0</ubPocketMapping>
	</ATTACHMENTSLOT>		
	<ATTACHMENTSLOT>
		<uiSlotIndex>35</uiSlotIndex>
		<szSlotName>电池</szSlotName>
		<nasAttachmentClass>2097152</nasAttachmentClass>
		<nasLayoutClass>1</nasLayoutClass>
		<usDescPanelPosX>147</usDescPanelPosX>
		<usDescPanelPosY>150</usDescPanelPosY>
		<fMultiShot>0</fMultiShot>
		<fBigSlot>0</fBigSlot>
		<ubPocketMapping>0</ubPocketMapping>
	</ATTACHMENTSLOT>	
	<ATTACHMENTSLOT>
		<uiSlotIndex>36</uiSlotIndex>
		<szSlotName>MOLLE 大腿装备左上</szSlotName>
		<nasAttachmentClass>4194304</nasAttachmentClass>
		<nasLayoutClass>4</nasLayoutClass>
		<usDescPanelPosX>187</usDescPanelPosX>
		<usDescPanelPosY>10</usDescPanelPosY>
		<fMultiShot>0</fMultiShot>
		<fBigSlot>0</fBigSlot>
		<ubPocketMapping>1</ubPocketMapping>
	</ATTACHMENTSLOT>	
	<ATTACHMENTSLOT>
		<uiSlotIndex>37</uiSlotIndex>
		<szSlotName>MOLLE 大腿装备右上</szSlotName>
		<nasAttachmentClass>4194304</nasAttachmentClass>
		<nasLayoutClass>4</nasLayoutClass>
		<usDescPanelPosX>223</usDescPanelPosX>
		<usDescPanelPosY>10</usDescPanelPosY>
		<fMultiShot>0</fMultiShot>
		<fBigSlot>0</fBigSlot>
		<ubPocketMapping>2</ubPocketMapping>
	</ATTACHMENTSLOT>		
	<ATTACHMENTSLOT>
		<uiSlotIndex>38</uiSlotIndex>
		<szSlotName>MOLLE 大腿装备左下</szSlotName>
		<nasAttachmentClass>4194304</nasAttachmentClass>
		<nasLayoutClass>4</nasLayoutClass>
		<usDescPanelPosX>187</usDescPanelPosX>
		<usDescPanelPosY>34</usDescPanelPosY>
		<fMultiShot>0</fMultiShot>
		<fBigSlot>0</fBigSlot>
		<ubPocketMapping>3</ubPocketMapping>
	</ATTACHMENTSLOT>	
	<ATTACHMENTSLOT>
		<uiSlotIndex>39</uiSlotIndex>
		<szSlotName>MOLLE 大腿装备右下</szSlotName>
		<nasAttachmentClass>4194304</nasAttachmentClass>
		<nasLayoutClass>4</nasLayoutClass>
		<usDescPanelPosX>223</usDescPanelPosX>
		<usDescPanelPosY>34</usDescPanelPosY>
		<fMultiShot>0</fMultiShot>
		<fBigSlot>0</fBigSlot>
		<ubPocketMapping>4</ubPocketMapping>
	</ATTACHMENTSLOT>	
	<ATTACHMENTSLOT>
		<uiSlotIndex>40</uiSlotIndex>
		<szSlotName>MOLLE 大腿装备底部中</szSlotName>
		<nasAttachmentClass>8388608</nasAttachmentClass>
		<nasLayoutClass>4</nasLayoutClass>
		<usDescPanelPosX>190</usDescPanelPosX>
		<usDescPanelPosY>58</usDescPanelPosY>
		<fMultiShot>0</fMultiShot>
		<fBigSlot>1</fBigSlot>
		<ubPocketMapping>5</ubPocketMapping>
	</ATTACHMENTSLOT>	
	<ATTACHMENTSLOT>
		<uiSlotIndex>41</uiSlotIndex>
		<szSlotName>MOLLE 背心上排 1</szSlotName>
		<nasAttachmentClass>4194304</nasAttachmentClass>
		<nasLayoutClass>8</nasLayoutClass>
		<usDescPanelPosX>10</usDescPanelPosX>
		<usDescPanelPosY>10</usDescPanelPosY>
		<fMultiShot>0</fMultiShot>
		<fBigSlot>0</fBigSlot>
		<ubPocketMapping>1</ubPocketMapping>
	</ATTACHMENTSLOT>
	<ATTACHMENTSLOT>
		<uiSlotIndex>42</uiSlotIndex>
		<szSlotName>MOLLE 背心上排 2</szSlotName>
		<nasAttachmentClass>4194304</nasAttachmentClass>
		<nasLayoutClass>8</nasLayoutClass>
		<usDescPanelPosX>46</usDescPanelPosX>
		<usDescPanelPosY>10</usDescPanelPosY>
		<fMultiShot>0</fMultiShot>
		<fBigSlot>0</fBigSlot>
		<ubPocketMapping>2</ubPocketMapping>
	</ATTACHMENTSLOT>
	<ATTACHMENTSLOT>
		<uiSlotIndex>43</uiSlotIndex>
		<szSlotName>MOLLE 背心上排 3</szSlotName>
		<nasAttachmentClass>4194304</nasAttachmentClass>
		<nasLayoutClass>8</nasLayoutClass>
		<usDescPanelPosX>82</usDescPanelPosX>
		<usDescPanelPosY>10</usDescPanelPosY>
		<fMultiShot>0</fMultiShot>
		<fBigSlot>0</fBigSlot>
		<ubPocketMapping>3</ubPocketMapping>
	</ATTACHMENTSLOT>
	<ATTACHMENTSLOT>
		<uiSlotIndex>44</uiSlotIndex>
		<szSlotName>MOLLE 背心上排 4</szSlotName>
		<nasAttachmentClass>4194304</nasAttachmentClass>
		<nasLayoutClass>8</nasLayoutClass>
		<usDescPanelPosX>118</usDescPanelPosX>
		<usDescPanelPosY>10</usDescPanelPosY>
		<fMultiShot>0</fMultiShot>
		<fBigSlot>0</fBigSlot>
		<ubPocketMapping>4</ubPocketMapping>
	</ATTACHMENTSLOT>
	<ATTACHMENTSLOT>
		<uiSlotIndex>45</uiSlotIndex>
		<szSlotName>MOLLE 背心上排 5</szSlotName>
		<nasAttachmentClass>4194304</nasAttachmentClass>
		<nasLayoutClass>8</nasLayoutClass>
		<usDescPanelPosX>154</usDescPanelPosX>
		<usDescPanelPosY>10</usDescPanelPosY>
		<fMultiShot>0</fMultiShot>
		<fBigSlot>0</fBigSlot>
		<ubPocketMapping>5</ubPocketMapping>
	</ATTACHMENTSLOT>	
	<ATTACHMENTSLOT>
		<uiSlotIndex>46</uiSlotIndex>
		<szSlotName>MOLLE 背心上排 6 中</szSlotName>
		<nasAttachmentClass>8388608</nasAttachmentClass>
		<nasLayoutClass>8</nasLayoutClass>
		<usDescPanelPosX>190</usDescPanelPosX>
		<usDescPanelPosY>10</usDescPanelPosY>
		<fMultiShot>0</fMultiShot>
		<fBigSlot>1</fBigSlot>
		<ubPocketMapping>11</ubPocketMapping>
	</ATTACHMENTSLOT>	
	<ATTACHMENTSLOT>
		<uiSlotIndex>47</uiSlotIndex>
		<szSlotName>MOLLE 背心下排 1</szSlotName>
		<nasAttachmentClass>4194304</nasAttachmentClass>
		<nasLayoutClass>8</nasLayoutClass>
		<usDescPanelPosX>10</usDescPanelPosX>
		<usDescPanelPosY>34</usDescPanelPosY>
		<fMultiShot>0</fMultiShot>
		<fBigSlot>0</fBigSlot>
		<ubPocketMapping>6</ubPocketMapping>
	</ATTACHMENTSLOT>
	<ATTACHMENTSLOT>
		<uiSlotIndex>48</uiSlotIndex>
		<szSlotName>MOLLE 背心下排 2</szSlotName>
		<nasAttachmentClass>4194304</nasAttachmentClass>
		<nasLayoutClass>8</nasLayoutClass>
		<usDescPanelPosX>46</usDescPanelPosX>
		<usDescPanelPosY>34</usDescPanelPosY>
		<fMultiShot>0</fMultiShot>
		<fBigSlot>0</fBigSlot>
		<ubPocketMapping>7</ubPocketMapping>
	</ATTACHMENTSLOT>
	<ATTACHMENTSLOT>
		<uiSlotIndex>49</uiSlotIndex>
		<szSlotName>MOLLE 背心下排 3</szSlotName>
		<nasAttachmentClass>4194304</nasAttachmentClass>
		<nasLayoutClass>8</nasLayoutClass>
		<usDescPanelPosX>82</usDescPanelPosX>
		<usDescPanelPosY>34</usDescPanelPosY>
		<fMultiShot>0</fMultiShot>
		<fBigSlot>0</fBigSlot>
		<ubPocketMapping>8</ubPocketMapping>
	</ATTACHMENTSLOT>
	<ATTACHMENTSLOT>
		<uiSlotIndex>50</uiSlotIndex>
		<szSlotName>MOLLE 背心下排 4</szSlotName>
		<nasAttachmentClass>4194304</nasAttachmentClass>
		<nasLayoutClass>8</nasLayoutClass>
		<usDescPanelPosX>118</usDescPanelPosX>
		<usDescPanelPosY>34</usDescPanelPosY>
		<fMultiShot>0</fMultiShot>
		<fBigSlot>0</fBigSlot>
		<ubPocketMapping>9</ubPocketMapping>
	</ATTACHMENTSLOT>
	<ATTACHMENTSLOT>
		<uiSlotIndex>51</uiSlotIndex>
		<szSlotName>MOLLE 背心下排 5</szSlotName>
		<nasAttachmentClass>4194304</nasAttachmentClass>
		<nasLayoutClass>8</nasLayoutClass>
		<usDescPanelPosX>154</usDescPanelPosX>
		<usDescPanelPosY>34</usDescPanelPosY>
		<fMultiShot>0</fMultiShot>
		<fBigSlot>0</fBigSlot>
		<ubPocketMapping>10</ubPocketMapping>
	</ATTACHMENTSLOT>	
	<ATTACHMENTSLOT>
		<uiSlotIndex>52</uiSlotIndex>
		<szSlotName>MOLLE 背心下排 6 中</szSlotName>
		<nasAttachmentClass>8388608</nasAttachmentClass>
		<nasLayoutClass>8</nasLayoutClass>
		<usDescPanelPosX>190</usDescPanelPosX>
		<usDescPanelPosY>34</usDescPanelPosY>
		<fMultiShot>0</fMultiShot>
		<fBigSlot>1</fBigSlot>
		<ubPocketMapping>12</ubPocketMapping>
	</ATTACHMENTSLOT>	
	<ATTACHMENTSLOT>
		<uiSlotIndex>53</uiSlotIndex>
		<szSlotName>MOLLE 腰带第一列 1</szSlotName>
		<nasAttachmentClass>4194304</nasAttachmentClass>
		<nasLayoutClass>16</nasLayoutClass>
		<usDescPanelPosX>118</usDescPanelPosX>
		<usDescPanelPosY>10</usDescPanelPosY>
		<fMultiShot>0</fMultiShot>
		<fBigSlot>0</fBigSlot>
		<ubPocketMapping>1</ubPocketMapping>
	</ATTACHMENTSLOT>
	<ATTACHMENTSLOT>
		<uiSlotIndex>54</uiSlotIndex>
		<szSlotName>MOLLE 腰带第一列 2</szSlotName>
		<nasAttachmentClass>4194304</nasAttachmentClass>
		<nasLayoutClass>16</nasLayoutClass>
		<usDescPanelPosX>118</usDescPanelPosX>
		<usDescPanelPosY>34</usDescPanelPosY>
		<fMultiShot>0</fMultiShot>
		<fBigSlot>0</fBigSlot>
		<ubPocketMapping>2</ubPocketMapping>
	</ATTACHMENTSLOT>		
	<ATTACHMENTSLOT>
		<uiSlotIndex>55</uiSlotIndex>
		<szSlotName>MOLLE 腰带第二列 1</szSlotName>
		<nasAttachmentClass>4194304</nasAttachmentClass>
		<nasLayoutClass>16</nasLayoutClass>
		<usDescPanelPosX>154</usDescPanelPosX>
		<usDescPanelPosY>10</usDescPanelPosY>
		<fMultiShot>0</fMultiShot>
		<fBigSlot>0</fBigSlot>
		<ubPocketMapping>3</ubPocketMapping>
	</ATTACHMENTSLOT>	
	<ATTACHMENTSLOT>
		<uiSlotIndex>56</uiSlotIndex>
		<szSlotName>MOLLE 腰带第二列 2</szSlotName>
		<nasAttachmentClass>4194304</nasAttachmentClass>
		<nasLayoutClass>16</nasLayoutClass>
		<usDescPanelPosX>154</usDescPanelPosX>
		<usDescPanelPosY>34</usDescPanelPosY>
		<fMultiShot>0</fMultiShot>
		<fBigSlot>0</fBigSlot>
		<ubPocketMapping>4</ubPocketMapping>
	</ATTACHMENTSLOT>			
	<ATTACHMENTSLOT>
		<uiSlotIndex>57</uiSlotIndex>
		<szSlotName>MOLLE 腰带第三列 1 中</szSlotName>
		<nasAttachmentClass>8388608</nasAttachmentClass>
		<nasLayoutClass>16</nasLayoutClass>
		<usDescPanelPosX>190</usDescPanelPosX>
		<usDescPanelPosY>10</usDescPanelPosY>
		<fMultiShot>0</fMultiShot>
		<fBigSlot>1</fBigSlot>
		<ubPocketMapping>5</ubPocketMapping>
	</ATTACHMENTSLOT>	
	<ATTACHMENTSLOT>
		<uiSlotIndex>58</uiSlotIndex>
		<szSlotName>MOLLE 腰带第三列 2</szSlotName>
		<nasAttachmentClass>4194304</nasAttachmentClass>
		<nasLayoutClass>16</nasLayoutClass>
		<usDescPanelPosX>207</usDescPanelPosX>
		<usDescPanelPosY>34</usDescPanelPosY>
		<fMultiShot>0</fMultiShot>
		<fBigSlot>0</fBigSlot>
		<ubPocketMapping>6</ubPocketMapping>
	</ATTACHMENTSLOT>	
	<ATTACHMENTSLOT>
		<uiSlotIndex>59</uiSlotIndex>
		<szSlotName>MOLLE 腰带第三列 3</szSlotName>
		<nasAttachmentClass>4194304</nasAttachmentClass>
		<nasLayoutClass>16</nasLayoutClass>
		<usDescPanelPosX>207</usDescPanelPosX>
		<usDescPanelPosY>58</usDescPanelPosY>
		<fMultiShot>0</fMultiShot>
		<fBigSlot>0</fBigSlot>
		<ubPocketMapping>7</ubPocketMapping>
	</ATTACHMENTSLOT>				
	<ATTACHMENTSLOT>
		<uiSlotIndex>60</uiSlotIndex>
		<szSlotName>MOLLE 背包第一列 1</szSlotName>
		<nasAttachmentClass>4194304</nasAttachmentClass>
		<nasLayoutClass>32</nasLayoutClass>
		<usDescPanelPosX>118</usDescPanelPosX>
		<usDescPanelPosY>10</usDescPanelPosY>
		<fMultiShot>0</fMultiShot>
		<fBigSlot>0</fBigSlot>
		<ubPocketMapping>1</ubPocketMapping>
	</ATTACHMENTSLOT>
	<ATTACHMENTSLOT>
		<uiSlotIndex>61</uiSlotIndex>
		<szSlotName>MOLLE 背包第一列 2</szSlotName>
		<nasAttachmentClass>4194304</nasAttachmentClass>
		<nasLayoutClass>32</nasLayoutClass>
		<usDescPanelPosX>118</usDescPanelPosX>
		<usDescPanelPosY>34</usDescPanelPosY>
		<fMultiShot>0</fMultiShot>
		<fBigSlot>0</fBigSlot>
		<ubPocketMapping>2</ubPocketMapping>
	</ATTACHMENTSLOT>			
	<ATTACHMENTSLOT>
		<uiSlotIndex>62</uiSlotIndex>
		<szSlotName>MOLLE 背包第二列 1</szSlotName>
		<nasAttachmentClass>4194304</nasAttachmentClass>
		<nasLayoutClass>32</nasLayoutClass>
		<usDescPanelPosX>154</usDescPanelPosX>
		<usDescPanelPosY>10</usDescPanelPosY>
		<fMultiShot>0</fMultiShot>
		<fBigSlot>0</fBigSlot>
		<ubPocketMapping>5</ubPocketMapping>
	</ATTACHMENTSLOT>	
	<ATTACHMENTSLOT>
		<uiSlotIndex>63</uiSlotIndex>
		<szSlotName>MOLLE 背包第二列 2</szSlotName>
		<nasAttachmentClass>4194304</nasAttachmentClass>
		<nasLayoutClass>32</nasLayoutClass>
		<usDescPanelPosX>154</usDescPanelPosX>
		<usDescPanelPosY>34</usDescPanelPosY>
		<fMultiShot>0</fMultiShot>
		<fBigSlot>0</fBigSlot>
		<ubPocketMapping>6</ubPocketMapping>
	</ATTACHMENTSLOT>		
	<ATTACHMENTSLOT>
		<uiSlotIndex>64</uiSlotIndex>
		<szSlotName>MOLLE 背包第三列 1 中</szSlotName>
		<nasAttachmentClass>8388608</nasAttachmentClass>
		<nasLayoutClass>32</nasLayoutClass>
		<usDescPanelPosX>190</usDescPanelPosX>
		<usDescPanelPosY>10</usDescPanelPosY>
		<fMultiShot>0</fMultiShot>
		<fBigSlot>1</fBigSlot>
		<ubPocketMapping>9</ubPocketMapping>
	</ATTACHMENTSLOT>		
	<ATTACHMENTSLOT>
		<uiSlotIndex>65</uiSlotIndex>
		<szSlotName>MOLLE 背包第三列 2 中</szSlotName>
		<nasAttachmentClass>8388608</nasAttachmentClass>
		<nasLayoutClass>32</nasLayoutClass>
		<usDescPanelPosX>190</usDescPanelPosX>
		<usDescPanelPosY>34</usDescPanelPosY>
		<fMultiShot>0</fMultiShot>
		<fBigSlot>1</fBigSlot>
		<ubPocketMapping>10</ubPocketMapping>
	</ATTACHMENTSLOT>	
	<ATTACHMENTSLOT>
		<uiSlotIndex>66</uiSlotIndex>
		<szSlotName>MOLLE 背包第三列 3 中</szSlotName>
		<nasAttachmentClass>8388608</nasAttachmentClass>
		<nasLayoutClass>32</nasLayoutClass>
		<usDescPanelPosX>190</usDescPanelPosX>
		<usDescPanelPosY>58</usDescPanelPosY>
		<fMultiShot>0</fMultiShot>
		<fBigSlot>1</fBigSlot>
		<ubPocketMapping>11</ubPocketMapping>
	</ATTACHMENTSLOT>		
	<ATTACHMENTSLOT>
		<uiSlotIndex>67</uiSlotIndex>
		<szSlotName>MOLLE 背包第三列 4 中</szSlotName>
		<nasAttachmentClass>8388608</nasAttachmentClass>
		<nasLayoutClass>32</nasLayoutClass>
		<usDescPanelPosX>190</usDescPanelPosX>
		<usDescPanelPosY>82</usDescPanelPosY>
		<fMultiShot>0</fMultiShot>
		<fBigSlot>1</fBigSlot>
		<ubPocketMapping>12</ubPocketMapping>
	</ATTACHMENTSLOT>	
	<ATTACHMENTSLOT>
		<uiSlotIndex>68</uiSlotIndex>
		<szSlotName>头盔附件：瞄准设备</szSlotName>
		<nasAttachmentClass>16777216</nasAttachmentClass>
		<nasLayoutClass>1</nasLayoutClass>
		<usDescPanelPosX>187</usDescPanelPosX>
		<usDescPanelPosY>66</usDescPanelPosY>
		<fMultiShot>0</fMultiShot>
		<fBigSlot>0</fBigSlot>
		<ubPocketMapping>0</ubPocketMapping>
	</ATTACHMENTSLOT>
	<ATTACHMENTSLOT>
		<uiSlotIndex>69</uiSlotIndex>
		<szSlotName>头盔附件：迷彩罩</szSlotName>
		<nasAttachmentClass>33554432</nasAttachmentClass>
		<nasLayoutClass>1</nasLayoutClass>
		<usDescPanelPosX>223</usDescPanelPosX>
		<usDescPanelPosY>66</usDescPanelPosY>
		<fMultiShot>0</fMultiShot>
		<fBigSlot>0</fBigSlot>
		<ubPocketMapping>0</ubPocketMapping>
	</ATTACHMENTSLOT>
	<ATTACHMENTSLOT>
		<uiSlotIndex>70</uiSlotIndex>
		<szSlotName>头盔附件：面部保护</szSlotName>
		<nasAttachmentClass>67108864</nasAttachmentClass>
		<nasLayoutClass>1</nasLayoutClass>
		<usDescPanelPosX>187</usDescPanelPosX>
		<usDescPanelPosY>94</usDescPanelPosY>
		<fMultiShot>0</fMultiShot>
		<fBigSlot>1</fBigSlot>
		<ubPocketMapping>0</ubPocketMapping>
	</ATTACHMENTSLOT>	
	<ATTACHMENTSLOT>
		<uiSlotIndex>71</uiSlotIndex>
		<szSlotName>背心附件：装甲板</szSlotName>
		<nasAttachmentClass>134217728</nasAttachmentClass>
		<nasLayoutClass>1</nasLayoutClass>
		<usDescPanelPosX>187</usDescPanelPosX>
		<usDescPanelPosY>80</usDescPanelPosY>
		<fMultiShot>0</fMultiShot>
		<fBigSlot>0</fBigSlot>
		<ubPocketMapping>0</ubPocketMapping>
	</ATTACHMENTSLOT>	
	<ATTACHMENTSLOT>
		<uiSlotIndex>72</uiSlotIndex>
		<szSlotName>背心附件：迷彩上衣</szSlotName>
		<nasAttachmentClass>268435456</nasAttachmentClass>
		<nasLayoutClass>1</nasLayoutClass>
		<usDescPanelPosX>223</usDescPanelPosX>
		<usDescPanelPosY>80</usDescPanelPosY>
		<fMultiShot>0</fMultiShot>
		<fBigSlot>0</fBigSlot>
		<ubPocketMapping>0</ubPocketMapping>
	</ATTACHMENTSLOT>		
	<ATTACHMENTSLOT>
		<uiSlotIndex>73</uiSlotIndex>
		<szSlotName>护腿附件：腿部保护器</szSlotName>
		<nasAttachmentClass>536870912</nasAttachmentClass>
		<nasLayoutClass>1</nasLayoutClass>
		<usDescPanelPosX>187</usDescPanelPosX>
		<usDescPanelPosY>80</usDescPanelPosY>
		<fMultiShot>0</fMultiShot>
		<fBigSlot>0</fBigSlot>
		<ubPocketMapping>0</ubPocketMapping>
	</ATTACHMENTSLOT>			
</ATTACHMENTSLOTLIST>
